AlbertUnruhUtils/__init__.py
AlbertUnruhUtils/asynchronous/__init__.py
AlbertUnruhUtils/asynchronous/ratelimit/__init__.py
AlbertUnruhUtils/asynchronous/ratelimit/server.py
AlbertUnruhUtils/config/__init__.py
AlbertUnruhUtils/config/jsonconfig.py
AlbertUnruhUtils/ratelimit/__init__.py
AlbertUnruhUtils/ratelimit/server.py
AlbertUnruhUtils/utils/__init__.py
AlbertUnruhUtils/utils/logger.py
AlbertUnruhUtils/utils/version.py
AlbertUnruhUtils-2022.1.29.2.dist-info/LICENSE
AlbertUnruhUtils-2022.1.29.2.dist-info/METADATA
AlbertUnruhUtils-2022.1.29.2.dist-info/WHEEL
AlbertUnruhUtils-2022.1.29.2.dist-info/top_level.txt
AlbertUnruhUtils-2022.1.29.2.dist-info/RECORD
