Metadata-Version: 2.1
Name: AlbertUnruhUtils
Version: 2022.1.29.2
Summary: A collection of utils written in Python.
Home-page: https://github.com/AlbertUnruh/AlbertUnruhUtils.py
Author: AlbertUnruh
License: MIT
Keywords: albert unruh utils configuration ratelimiting sync async logging version
Platform: UNKNOWN
Classifier: Intended Audience :: Developers
Classifier: License :: OSI Approved :: MIT License
Classifier: Operating System :: OS Independent
Classifier: Programming Language :: Python :: 3
Classifier: Programming Language :: Python :: 3.9
Classifier: Programming Language :: Python :: 3.10
Classifier: Programming Language :: Python :: 3.11
Classifier: Topic :: Software Development :: Libraries
Classifier: Topic :: Software Development :: Libraries :: Python Modules
Classifier: Topic :: Utilities
Classifier: Typing :: Typed
Requires-Python: >=3.9
License-File: LICENSE
Requires-Dist: redis (~=4.1.0)
Requires-Dist: aioredis (~=2.0.1)
